[
    {
      "icon": "bi bi-code-slash",
      "title": "Frontend Development",
      "description": "Responsive, animated websites built with React & SCSS.",
      "link": "/services/frontend"
    },
    {
      "icon": "bi bi-brush",
      "title": "Web Design & Branding",
      "description": "Transforming ideas into beautiful digital experiences.",
      "link": "/services/design"
    },
    {
      "icon": "bi bi-wordpress",
      "title": "WordPress Themes",
      "description": "Custom themes and integrations built for performance.",
      "link": "/services/wordpress"
    },
    {
      "icon": "bi bi-lightning-charge",
      "title": "AI & Automation",
      "description": "Smart integrations to make your workflow efficient.",
      "link": "/services/automation"
    },
    {
      "icon": "bi bi-cloud-arrow-up",
      "title": "Deployment & SEO",
      "description": "Optimized hosting, SEO setup, and maintenance.",
      "link": "/services/seo"
    },
    {
      "icon": "bi bi-chat-left-heart",
      "title": "Consulting",
      "description": "Personalized advice for building your digital identity.",
      "link": "/services/consulting"
    }
  ]